bitwarden_import_msecure/__about__.py
bitwarden_import_msecure/__init__.py
bitwarden_import_msecure/bitwarden_csv.py
bitwarden_import_msecure/bitwarden_json.py
bitwarden_import_msecure/main.py
bitwarden_import_msecure/msecure.py
bitwarden_import_msecure/msecure_to_bitwarden.py
bitwarden_import_msecure-1.7.3.dist-info/METADATA
bitwarden_import_msecure-1.7.3.dist-info/WHEEL
bitwarden_import_msecure-1.7.3.dist-info/entry_points.txt
bitwarden_import_msecure-1.7.3.dist-info/licenses/LICENSE.txt
bitwarden_import_msecure-1.7.3.dist-info/RECORD
