Metadata-Version: 2.4
Name: bitwarden-import-msecure
Version: 1.7.3
Summary: Migration from mSecure to Bitwarden
Project-URL: Homepage, https://andgineer.github.io/bitwarden-import-msecure/
Project-URL: Documentation, https://andgineer.github.io/bitwarden-import-msecure/
Author-email: Andrey Sorokin <andrey@sorokin.engineer>
License: Copyright (c) 2024 Andrey Sorokin <andrey@sorokin.engineer>
License-File: LICENSE.txt
Keywords: bitwarden,export,import,mSecure,migration,passwords
Classifier: License :: OSI Approved :: MIT License
Classifier: Operating System :: OS Independent
Classifier: Programming Language :: Python :: 3
Requires-Python: >=3.9
Requires-Dist: click
Requires-Dist: rich-click
